{
    "changelog": [
        {
            "comments": [
                "Migrated from v1.4",
                "Updated compound(s) information (NPAtlas curation)"
            ],
            "version": "2.0"
        }
    ],
    "cluster": {
        "biosyn_class": [
            "Polyketide"
        ],
        "compounds": [
            {
                "chem_struct": "CCCC1CC2=CC3=C(C(O)=C2C(=O)O1)C1=C(O)C2=C(OC4=C(C(O)=C(O[C@H]5C[C@@H](O)[C@H](O[C@H]6C[C@@H](O)[C@H](O[C@H]7C[C@@H](OC)[C@H](O)[C@@H](C)O7)[C@@H](C)O6)[C@@H](C)O5)C=C4)C2=O)C(OC)=C1C(O)C3O",
                "compound": "FD-594",
                "database_id": [
                    "npatlas:1710"
                ],
                "mol_mass": 1304.7448,
                "molecular_formula": "C61H12O35"
            }
        ],
        "loci": {
            "accession": "AB469194.1",
            "completeness": "Unknown"
        },
        "mibig_accession": "BGC0000222",
        "minimal": true,
        "ncbi_tax_id": "573242",
        "organism_name": "Streptomyces sp. TA-0256",
        "publications": [
            "pubmed:21102601"
        ]
    }
}