{
    "changelog": [
        {
            "comments": [
                "Entry added"
            ],
            "contributors": [
                "AAAAAAAAAAAAAAAAAAAAAAAA"
            ],
            "version": "3.0"
        }
    ],
    "cluster": {
        "biosyn_class": [
            "Other"
        ],
        "compounds": [
            {
                "chem_struct": "CC(C)CCCCCCCCC/C=C/C(=O)N[C@@H]1[C@H]([C@H]([C@H](O[C@H]1O[C@H]2[C@H]([C@@H]([C@H]([C@@H](O2)CO)O)O)NC(=O)C)C[C@H]([C@@H]3[C@H]([C@H]([C@@H](O3)N4C=CC(=O)NC4=O)O)O)O)O)O",
                "compound": "tunicamycin",
                "database_id": [
                    "npatlas:NPA024688"
                ]
            }
        ],
        "loci": {
            "accession": "MH813486.1",
            "completeness": "Unknown",
            "end_coord": 14110,
            "start_coord": 1
        },
        "mibig_accession": "BGC0002553",
        "minimal": true,
        "ncbi_tax_id": "59737",
        "organism_name": "Rathayibacter iranicus",
        "publications": [
            "pubmed:31998251",
            "doi:10.3389/fmicb.2019.02914"
        ],
        "status": "active"
    }
}