{
    "changelog": [
        {
            "comments": [
                "Entry added"
            ],
            "contributors": [
                "AAAAAAAAAAAAAAAAAAAAAAAA"
            ],
            "version": "3.0"
        }
    ],
    "cluster": {
        "biosyn_class": [
            "NRP"
        ],
        "compounds": [
            {
                "compound": "histicorrugatin"
            }
        ],
        "loci": {
            "accession": "LT629691.1",
            "completeness": "Unknown",
            "end_coord": 1678052,
            "start_coord": 1634212
        },
        "mibig_accession": "BGC0002422",
        "minimal": true,
        "ncbi_tax_id": "86265",
        "organism_name": "Pseudomonas thivervalensis",
        "publications": [
            "pubmed:27007713"
        ],
        "status": "active"
    }
}