{
    "changelog": [
        {
            "comments": [
                "Entry added"
            ],
            "contributors": [
                "AAAAAAAAAAAAAAAAAAAAAAAA"
            ],
            "version": "3.0"
        },
        {
            "comments": [
                "Added chemical structures for compounds: vibriobactin.",
                "Added NPAtlas links to compounds: vibriobactin."
            ],
            "contributors": [
                "AAAAAAAAAAAAAAAAAAAAAAAA"
            ],
            "version": "3.1"
        }
    ],
    "cluster": {
        "biosyn_class": [
            "NRP"
        ],
        "compounds": [
            {
                "chem_struct": "C[C@@H]1OC(C2=C(O)C(O)=CC=C2)=N[C@H]1C(=O)NCCCN(CCCNC(=O)C1=C(O)C(O)=CC=C1)C(=O)[C@H]1N=C(C2=C(O)C(O)=CC=C2)O[C@@H]1C",
                "compound": "vibriobactin",
                "database_id": [
                    "npatlas:NPA033096"
                ]
            }
        ],
        "loci": {
            "accession": "U52150.2",
            "completeness": "Unknown",
            "evidence": [
                "Heterologous expression"
            ]
        },
        "mibig_accession": "BGC0002494",
        "minimal": true,
        "ncbi_tax_id": "666",
        "organism_name": "Vibrio cholerae",
        "publications": [
            "pubmed:10601218",
            "doi:10.1128/JB.181.24.7588-7596.1999"
        ],
        "status": "active"
    }
}