{
    "changelog": [
        {
            "comments": [
                "Entry added"
            ],
            "contributors": [
                "AAAAAAAAAAAAAAAAAAAAAAAA"
            ],
            "version": "3.0"
        }
    ],
    "cluster": {
        "biosyn_class": [
            "Alkaloid"
        ],
        "compounds": [
            {
                "chem_struct": "NC1=NC(/C=C/CC2=CC=CC=C2)=C3N1CCC3",
                "compound": "massinidine"
            }
        ],
        "loci": {
            "accession": "CP012201.1",
            "completeness": "Unknown",
            "end_coord": 4384749,
            "evidence": [
                "Heterologous expression"
            ],
            "start_coord": 4381188
        },
        "mibig_accession": "BGC0002647",
        "minimal": true,
        "ncbi_tax_id": "1678028",
        "organism_name": "Massilia sp. NR 4-1",
        "publications": [
            "pubmed:35412834"
        ],
        "status": "active"
    }
}