{
    "changelog": [
        {
            "comments": [
                "Entry added"
            ],
            "contributors": [
                "AAAAAAAAAAAAAAAAAAAAAAAA"
            ],
            "version": "3.0"
        }
    ],
    "cluster": {
        "biosyn_class": [
            "NRP",
            "Polyketide"
        ],
        "compounds": [
            {
                "compound": "colibromycin A"
            },
            {
                "compound": "colibromycin B"
            },
            {
                "compound": "colibromycin C"
            }
        ],
        "loci": {
            "accession": "KZ819182.1",
            "completeness": "Unknown",
            "end_coord": 4779057,
            "evidence": [
                "Knock-out studies"
            ],
            "start_coord": 4724124
        },
        "mibig_accession": "BGC0002590",
        "minimal": true,
        "ncbi_tax_id": "2162715",
        "organism_name": "Streptomyces sp. CS147",
        "publications": [
            "pubmed:34669429",
            "doi:10.1128/AEM.01839-21"
        ],
        "retirement_reasons": [
            "Duplicate of BGC0002100"
        ],
        "see_also": [
            "BGC0002100"
        ],
        "status": "retired"
    }
}