{
    "changelog": [
        {
            "comments": [
                "Entry added"
            ],
            "contributors": [
                "AAAAAAAAAAAAAAAAAAAAAAAA"
            ],
            "version": "3.0"
        }
    ],
    "cluster": {
        "biosyn_class": [
            "Polyketide"
        ],
        "compounds": [
            {
                "chem_struct": "C[C@H]1/C=C(/C(CC(=O)N(C2=C(C(=CC(=C2)C/C(=C/C=C/[C@H]([C@]3(C[C@@H]1OC(=O)N3)OC)OC)/C)O)Cl)[C@H]4[C@@H]([C@H]([C@@H]([C@H](O4)COC(=O)C)OC(=O)N)OC)O)OC(=O)NC)\\C",
                "compound": "ansacarbamitocin",
                "database_id": [
                    "npatlas:NPA024184"
                ]
            }
        ],
        "loci": {
            "accession": "MK934297.1",
            "completeness": "Unknown",
            "end_coord": 82440,
            "evidence": [
                "Gene expression correlated with compound production",
                "Enzymatic assays"
            ],
            "start_coord": 1
        },
        "mibig_accession": "BGC0002552",
        "minimal": true,
        "ncbi_tax_id": "411144",
        "organism_name": "Amycolatopsis sp. CP2808",
        "publications": [
            "pubmed:31299158",
            "doi:10.1021/acs.orglett.9b01891"
        ],
        "status": "active"
    }
}