{
    "changelog": [
        {
            "comments": [
                "Submitted"
            ],
            "contributors": [
                "AAAAAAAAAAAAAAAAAAAAAAAA"
            ],
            "version": "2.0"
        }
    ],
    "cluster": {
        "biosyn_class": [
            "Terpene"
        ],
        "compounds": [
            {
                "compound": "atolypene A"
            },
            {
                "compound": "atolypene B"
            }
        ],
        "loci": {
            "accession": "NZ_FNSO01000004.1",
            "completeness": "Unknown",
            "end_coord": 5943258,
            "start_coord": 5921897
        },
        "mibig_accession": "BGC0002007",
        "minimal": true,
        "ncbi_tax_id": "208445",
        "organism_name": "Amycolatopsis tolypomycina",
        "publications": [
            "pubmed:30575381"
        ],
        "status": "active"
    }
}