{
    "changelog": [
        {
            "comments": [
                "Entry added"
            ],
            "contributors": [
                "AAAAAAAAAAAAAAAAAAAAAAAA"
            ],
            "version": "3.0"
        }
    ],
    "cluster": {
        "biosyn_class": [
            "Polyketide",
            "NRP"
        ],
        "compounds": [
            {
                "chem_struct": "CO/[N+]([O-])=C/C(=O)N/C=C/C(=O)O",
                "compound": "enteromycin",
                "database_id": [
                    "npatlas:NPA018410"
                ]
            }
        ],
        "loci": {
            "accession": "MW367897.1",
            "completeness": "Unknown",
            "end_coord": 24026,
            "evidence": [
                "Heterologous expression"
            ],
            "start_coord": 1
        },
        "mibig_accession": "BGC0002499",
        "minimal": true,
        "ncbi_tax_id": "285532",
        "organism_name": "Streptomyces achromogenes subsp. streptozoticus",
        "publications": [
            "pubmed:33782561"
        ],
        "status": "active"
    }
}