{
    "changelog": [
        {
            "comments": [
                "Entry added"
            ],
            "contributors": [
                "AAAAAAAAAAAAAAAAAAAAAAAA"
            ],
            "version": "3.0"
        }
    ],
    "cluster": {
        "biosyn_class": [
            "Polyketide",
            "NRP"
        ],
        "compounds": [
            {
                "chem_struct": "CC(=O)[C@H]1[C@@H]2C=C[C@@H]3[C@@H](C/C=C\\C(N)=O)[C@H](/C=C/C(O)=C4C(=O)N[C@@H](CCC(=O)O)C4=O)C[C@@H]3[C@H]2C[C@H]1C",
                "compound": "clifednamide D",
                "database_id": [
                    "npatlas:NPA029427"
                ]
            },
            {
                "chem_struct": "C[C@@H]1C[C@H]2[C@@H](C=C[C@@H]3[C@H]4C/C=C\\C(=O)NCC[C@H](O)[C@@H]5NC(=O)C(=C(O)/C=C/[C@@H]4C[C@@H]32)C5=O)[C@@H]1C(=O)CO",
                "compound": "clifednamide E",
                "database_id": [
                    "npatlas:NPA029428"
                ]
            },
            {
                "chem_struct": "CC(=O)[C@H]1[C@@H]2C=C[C@@H]3/C=C/C=C/C(=O)NCCC[C@@H]4NC(=O)C(=C(O)/C=C/C=C/[C@@H]3[C@H]2C[C@H]1C)C4=O",
                "compound": "clifednamide F",
                "database_id": [
                    "npatlas:NPA029429"
                ]
            },
            {
                "chem_struct": "CC(=O)[C@H]1[C@@H]2C=C[C@H](/C=C/C=C/C(N)=O)[C@H](/C=C/C=C/C(O)=C3C(=O)N[C@@H](CCC(=O)O)C3=O)[C@H]2C[C@H]1C",
                "compound": "clifednamide G",
                "database_id": [
                    "npatlas:NPA029430"
                ]
            },
            {
                "chem_struct": "CC[C@H]1[C@@H]2C=C[C@H](/C=C/C=C/C(N)=O)[C@H](/C=C/C=C/C(O)=C3C(=O)N[C@@H](CCC(=O)O)C3=O)[C@H]2C[C@H]1C",
                "compound": "clifednamide H",
                "database_id": [
                    "npatlas:NPA029431"
                ]
            },
            {
                "chem_struct": "CC(=O)[C@H]1[C@@H]2C=C[C@@H]3/C=C/C=C/C(=O)NCC[C@H](O)[C@@H]4NC(=O)C(=C(O)/C=C/C=C/[C@@H]3[C@H]2C[C@H]1C)C4=O",
                "compound": "clifednamide I",
                "database_id": [
                    "npatlas:NPA029432"
                ]
            },
            {
                "chem_struct": "CC(O)[C@H]1[C@@H]2C=C[C@@H]3/C=C/C=C/C(=O)NCC[C@H](O)[C@@H]4NC(=O)C(=C(O)/C=C/C=C/[C@@H]3[C@H]2C[C@H]1C)C4=O",
                "compound": "clifednamide J",
                "database_id": [
                    "npatlas:NPA029433"
                ]
            }
        ],
        "loci": {
            "accession": "MT419890.1",
            "completeness": "Unknown",
            "evidence": [
                "Heterologous expression"
            ]
        },
        "mibig_accession": "BGC0002434",
        "minimal": true,
        "ncbi_tax_id": "1871188",
        "organism_name": "Kitasatospora sp.",
        "publications": [
            "pubmed:32915576",
            "doi:10.1021/acs.jnatprod.0c00900"
        ],
        "status": "active"
    }
}