{
    "changelog": [
        {
            "comments": [
                "Submitted"
            ],
            "contributors": [
                "AAAAAAAAAAAAAAAAAAAAAAAA"
            ],
            "version": "1.4"
        },
        {
            "comments": [
                "Migrated from v1.4",
                "Updated compound(s) information (NPAtlas curation)"
            ],
            "contributors": [
                "AAAAAAAAAAAAAAAAAAAAAAAA"
            ],
            "version": "2.0"
        },
        {
            "comments": [
                "Updated bioactivity data"
            ],
            "contributors": [
                "AAAAAAAAAAAAAAAAAAAAAAAA"
            ],
            "version": "3.0"
        },
        {
            "comments": [
                "Update chemical activity to schema version 2.11"
            ],
            "contributors": [
                "AAAAAAAAAAAAAAAAAAAAAAAA"
            ],
            "version": "3.1"
        }
    ],
    "cluster": {
        "biosyn_class": [
            "Other"
        ],
        "compounds": [
            {
                "chem_acts": [
                    {
                        "activity": "antibacterial"
                    },
                    {
                        "activity": "cytotoxic"
                    }
                ],
                "chem_struct": "OC[C@H]1O[C@H]([C@H](O)[C@@H]1O)C1=CC(=O)NC1=O",
                "compound": "showdomycin",
                "database_id": [
                    "npatlas:NPA012925"
                ],
                "mol_mass": 229.058637072,
                "molecular_formula": "C9H11NO6"
            }
        ],
        "loci": {
            "accession": "LAQS01000018.1",
            "completeness": "Unknown",
            "end_coord": 29440,
            "start_coord": 12966
        },
        "mibig_accession": "BGC0001778",
        "minimal": true,
        "ncbi_tax_id": "68268",
        "organism_name": "Streptomyces showdoensis",
        "publications": [
            "pubmed:28418235"
        ],
        "status": "active"
    }
}