{
    "changelog": [
        {
            "comments": [
                "Submitted"
            ],
            "contributors": [
                "AAAAAAAAAAAAAAAAAAAAAAAA"
            ],
            "version": "1.4"
        },
        {
            "comments": [
                "Migrated from v1.4"
            ],
            "contributors": [
                "AAAAAAAAAAAAAAAAAAAAAAAA"
            ],
            "version": "2.0"
        }
    ],
    "cluster": {
        "biosyn_class": [
            "RiPP"
        ],
        "compounds": [
            {
                "compound": "cattlecin"
            }
        ],
        "loci": {
            "accession": "FQ859185.1",
            "completeness": "Unknown",
            "end_coord": 79728,
            "start_coord": 77019
        },
        "mibig_accession": "BGC0001539",
        "minimal": true,
        "ncbi_tax_id": "1003195",
        "organism_name": "Streptomyces cattleya NRRL 8057 = DSM 46488",
        "publications": [
            "doi:10.1007/s13765-017-0268-x"
        ]
    }
}