{
    "changelog": [
        {
            "comments": [
                "Entry added"
            ],
            "contributors": [
                "AAAAAAAAAAAAAAAAAAAAAAAA"
            ],
            "version": "3.0"
        }
    ],
    "cluster": {
        "biosyn_class": [
            "NRP"
        ],
        "compounds": [
            {
                "chem_struct": "CCCCCCCC(O)CC(=O)NC(CC(C)C)C(=O)NC(CC(=O)O)C(=O)NC1C(=O)NC(CC(C)C)C(=O)NC(CC(C)C)C(=O)NC(CO)C(=O)NC(CC(C)C)C(=O)NC(C(C)CC)C(=O)OC1C",
                "compound": "bananamide F",
                "database_id": [
                    "npatlas:NPA026208"
                ]
            },
            {
                "chem_struct": "CCCCCCC/C=C\\C(O)CC(=O)NC(CC(C)C)C(=O)NC(CC(=O)O)C(=O)NC1C(=O)NC(CC(C)C)C(=O)NC(CC(C)C)C(=O)NC(CO)C(=O)NC(CC(C)C)C(=O)NC(C(C)CC)C(=O)OC1C",
                "compound": "bananamide D",
                "database_id": [
                    "npatlas:NPA026209"
                ]
            },
            {
                "chem_struct": "CCCCCCC/C=C\\C(O)CC(=O)NC(CC(C)C)C(=O)NC(CC(=O)O)C(=O)NC1C(=O)NC(CC(C)C)C(=O)NC(CC(C)C)C(=O)NC(CO)C(=O)NC(CC(C)C)C(=O)NC(C(C)C)C(=O)OC1C",
                "compound": "bananamide G",
                "database_id": [
                    "npatlas:NPA026210"
                ]
            },
            {
                "chem_struct": "CCCCCCCCCC(O)CC(=O)NC(CC(C)C)C(=O)NC(CC(=O)O)C(=O)NC1C(=O)NC(CC(C)C)C(=O)NC(CC(C)C)C(=O)NC(CO)C(=O)NC(CC(C)C)C(=O)NC(C(C)CC)C(=O)OC1C",
                "compound": "bananamide E",
                "database_id": [
                    "npatlas:NPA026211"
                ]
            }
        ],
        "loci": {
            "accession": "MN480426.1",
            "completeness": "Unknown",
            "end_coord": 34614,
            "start_coord": 1
        },
        "mibig_accession": "BGC0002548",
        "minimal": true,
        "ncbi_tax_id": "306",
        "organism_name": "Pseudomonas sp.",
        "publications": [
            "pubmed:31744250",
            "doi:10.3390/molecules24224170"
        ],
        "status": "active"
    }
}