{
    "changelog": [
        {
            "comments": [
                "Submitted"
            ],
            "contributors": [
                "AAAAAAAAAAAAAAAAAAAAAAAA"
            ],
            "version": "1.0"
        },
        {
            "comments": [
                "Migrated from v1.4",
                "Updated compound(s) information (NPAtlas curation)"
            ],
            "contributors": [
                "AAAAAAAAAAAAAAAAAAAAAAAA"
            ],
            "version": "2.0"
        },
        {
            "comments": [
                "Updated bioactivity data"
            ],
            "contributors": [
                "AAAAAAAAAAAAAAAAAAAAAAAA"
            ],
            "version": "3.0"
        },
        {
            "comments": [
                "Update chemical activity to schema version 2.11"
            ],
            "contributors": [
                "AAAAAAAAAAAAAAAAAAAAAAAA"
            ],
            "version": "3.1"
        }
    ],
    "cluster": {
        "biosyn_class": [
            "NRP",
            "Polyketide"
        ],
        "compounds": [
            {
                "chem_acts": [
                    {
                        "activity": "antibacterial"
                    },
                    {
                        "activity": "cytotoxic"
                    },
                    {
                        "activity": "immunosuppressive"
                    }
                ],
                "chem_struct": "[H][C@]12C[C@]([H])(O)\\C=C\\C(\\C)=C\\C[C@]([H])(O)\\C=C\\C(\\C)=C\\[C@@]([H])(NC(=O)C(C)=O)[C@](C)(C(=O)O1)C(=O)[C@@H]2C",
                "compound": "lankacidin C",
                "database_id": [
                    "npatlas:NPA04098"
                ],
                "mol_mass": 459.2257023959999,
                "molecular_formula": "C25H33NO7"
            }
        ],
        "loci": {
            "accession": "AB088224.2",
            "completeness": "Unknown",
            "end_coord": 35881,
            "start_coord": 4922
        },
        "mibig_accession": "BGC0001100",
        "minimal": true,
        "ncbi_tax_id": "1928",
        "organism_name": "Streptomyces rochei",
        "publications": [
            "pubmed:12791134",
            "pubmed:10954087",
            "pubmed:10767533",
            "pubmed:9836424"
        ],
        "status": "active"
    }
}